LICENSE
MANIFEST.in
README.rst
setup.cfg
setup.py
gscli/__init__.py
gscli/commands.py
gscli/config.py
gscli/group.py
gscli/i18n.py
gscli/parsers.py
gscli/status.py
gscli/user.py
gscli/util.py
gscli/validation.py
gscli.egg-info/PKG-INFO
gscli.egg-info/SOURCES.txt
gscli.egg-info/dependency_links.txt
gscli.egg-info/requires.txt
gscli.egg-info/top_level.txt
gscli/locale/messages.pot
gscli/locale/ru/LC_MESSAGES/messages.mo
gscli/locale/ru/LC_MESSAGES/messages.po
scripts/gscli