Metadata-Version: 1.1
Name: gscli
Version: 1.2.3
Summary: Command-line shell for GNU Social
Home-page: https://gitgud.io/dtluna/gscli
Author: dtluna
Author-email: dtluna@openmailbox.org
License: GPLv3
Platform: any
Classifier: License :: OSI Approved :: GNU General Public License v3 (GPLv3)
Classifier: Operating System :: OS Independent
Classifier: Programming Language :: Python :: 3
